l_03_requests_cmd_publish_lib/__init__.py
l_03_requests_cmd_publish_lib/simple_requests.py
l_03_requests_cmd_publish_lib-0.1.0.dist-info/entry_points.txt
l_03_requests_cmd_publish_lib-0.1.0.dist-info/WHEEL
l_03_requests_cmd_publish_lib-0.1.0.dist-info/METADATA
l_03_requests_cmd_publish_lib-0.1.0.dist-info/RECORD
