Metadata-Version: 2.1
Name: l-03-requests-cmd-publish-lib
Version: 0.1.0
Summary: 
Author: Rustem Saitgareev
Author-email: rus.saitgareev@gmail.com
Requires-Python: >=3.8,<4.0
Classifier: Programming Language :: Python :: 3
Classifier: Programming Language :: Python :: 3.8
Classifier: Programming Language :: Python :: 3.9
Requires-Dist: click (>=7.1.2,<8.0.0)
Requires-Dist: pytest-mock (>=3.6.0,<4.0.0)
Requires-Dist: requests (>=2.25.1,<3.0.0)
